indicatorfortune/CHANGELOG.md
indicatorfortune/__init__.py
indicatorfortune/indicatorbase.py
indicatorfortune/indicatorfortune.py
indicatorfortune/icons/Adwaita/indicatorfortune.svg
indicatorfortune/icons/Ambiant-MATE/indicatorfortune.svg
indicatorfortune/icons/Lubuntu/indicatorfortune.svg
indicatorfortune/icons/Papirus/indicatorfortune.svg
indicatorfortune/icons/Papirus-Light/indicatorfortune.svg
indicatorfortune/icons/Pocillo/indicatorfortune.svg
indicatorfortune/icons/Yaru/indicatorfortune.svg
indicatorfortune/icons/Yaru-MATE-dark/indicatorfortune.svg
indicatorfortune/icons/Yaru-MATE-light/indicatorfortune.svg
indicatorfortune/icons/Yaru-unity-dark/indicatorfortune.svg
indicatorfortune/icons/Yaru-unity-light/indicatorfortune.svg
indicatorfortune/icons/breeze/indicatorfortune.svg
indicatorfortune/icons/breeze-dark/indicatorfortune.svg
indicatorfortune/icons/ePapirus/indicatorfortune.svg
indicatorfortune/icons/elementary-xfce-darker/indicatorfortune.svg
indicatorfortune/icons/hicolor/indicatorfortune.svg
indicatorfortune/icons/ubuntu-mono-dark/indicatorfortune.svg
indicatorfortune/icons/ubuntu-mono-light/indicatorfortune.svg
indicatorfortune/locale/indicatorfortune.pot
indicatorfortune/locale/ru/LC_MESSAGES/indicatorfortune.mo
indicatorfortune/locale/ru/LC_MESSAGES/indicatorfortune.po
indicatorfortune/packaging/linux/indicatorfortune.py.desktop
indicatorfortune/packaging/linux/indicatorfortune.sh
indicatorfortune-1.0.43.dist-info/METADATA
indicatorfortune-1.0.43.dist-info/WHEEL
indicatorfortune-1.0.43.dist-info/top_level.txt
indicatorfortune-1.0.43.dist-info/RECORD
