Metadata-Version: 2.1
Name: indicatorfortune
Version: 1.0.43
Summary: Application indicator which displays fortunes.
Author-email: Bernard Giannetti <thebernmeister@hotmail.com>
Maintainer-email: Bernard Giannetti <thebernmeister@hotmail.com>
Project-URL: homepage, https://pypi.org/project/indicatorfortune
Classifier: Development Status :: 6 - Mature
Classifier: Environment :: X11 Applications :: GTK
Classifier: Intended Audience :: End Users/Desktop
Classifier: License :: OSI Approved :: GNU General Public License v3 or later (GPLv3+)
Classifier: Natural Language :: English
Classifier: Operating System :: POSIX :: Linux
Classifier: Programming Language :: Python :: 3.8
Classifier: Topic :: Games/Entertainment :: Fortune Cookies
Requires-Python: >=3.8
Requires-Dist: PyGObject
